[{"rank":1,"url":"https://qiita.com/mikan3rd/items/ba4737023f08bb2ca161","user":{"profile_image_url":"https://avatars2.githubusercontent.com/u/27764298?v=3","id":"mikan3rd","twitter_screen_name":"mikan_the_third"},"id":"ba4737023f08bb2ca161","created_at":"2018-09-17T21:12:27+09:00","title":"[2018] 個人でも使える！おすすめAPI一覧","tags":[{"name":"Python"},{"name":"Instagram"},{"name":"GoogleCloudPlatform"}],"score":"461.0"},{"rank":2,"url":"https://qiita.com/wtetsu/items/c43232c6c44918e977c9","user":{"profile_image_url":"https://qiita-image-store.s3.amazonaws.com/0/106401/profile-images/1494858105","id":"wtetsu","twitter_screen_name":"wtetsu"},"id":"c43232c6c44918e977c9","created_at":"2018-09-05T00:06:08+09:00","title":"Chrome拡張の高速な英語辞書ツールをつくりました","tags":[{"name":"Chrome"},{"name":"chrome-extension"},{"name":"English"}],"score":"424.8"},{"rank":3,"url":"https://qiita.com/tkrkt/items/2fc9a9a59ce679aab728","user":{"id":"tkrkt","profile_image_url":"https://qiita-image-store.s3.amazonaws.com/0/60243/profile-images/1473695175"},"id":"2fc9a9a59ce679aab728","created_at":"2018-09-20T21:19:45+09:00","title":"なぜ我々はいまだに文字列でコメントを書いているのか","tags":[{"name":"コメント"},{"name":"VSCode"}],"score":"338.9"},{"rank":4,"url":"https://qiita.com/shunichi_com/items/b07ae8c678aa7c0e2ff6","user":{"id":"shunichi_com","profile_image_url":"https://qiita-image-store.s3.amazonaws.com/0/239829/profile-images/1537568946"},"id":"b07ae8c678aa7c0e2ff6","created_at":"2018-09-21T17:04:55+09:00","title":"Sequel Proを超えるGUIツールが出てきたぞ","tags":[{"name":"MySQL"},{"name":"Redis"},{"name":"SQL"},{"name":"PostgreSQL"},{"name":"oracle"}],"score":"253.1"},{"rank":5,"url":"https://qiita.com/yokoyan/items/2e4cef0728aaf8d2e7d8","user":{"profile_image_url":"https://qiita-image-store.s3.amazonaws.com/0/98130/profile-images/1503203441","id":"yokoyan","twitter_screen_name":"yokoyantech"},"id":"2e4cef0728aaf8d2e7d8","created_at":"2018-09-25T16:06:16+09:00","title":"【AWS】アカウント契約の準拠法をワシントン州法から日本法に、管轄裁判所をワシントン州キング群州裁判所から東京裁判所に変更する方法","tags":[{"name":"AWS"},{"name":"要件定義"},{"name":"契約"},{"name":"非機能要件"},{"name":"AWSArtifact"}],"score":"230.9"},{"rank":6,"url":"https://qiita.com/k-okina/items/512b9e502f8db49981f3","user":{"profile_image_url":"https://qiita-image-store.s3.amazonaws.com/0/141711/profile-images/1527927706","id":"k-okina","twitter_screen_name":"kahirokunn"},"id":"512b9e502f8db49981f3","created_at":"2018-09-13T11:30:34+09:00","title":"2018年Vue.jsとVuexを使ってる人には必ず知っていてほしいドキュメントに書かれていないコンポーネントやストア、メンテナンスの際に役立つTips","tags":[{"name":"TypeScript"},{"name":"es6"},{"name":"DesignPatterns"},{"name":"vue.js"},{"name":"Vuex"}],"score":"228.4"},{"rank":7,"url":"https://qiita.com/0w0/items/07a481921a2ac09a049f","user":{"profile_image_url":"https://qiita-image-store.s3.amazonaws.com/0/154302/profile-images/1505133762","id":"0w0","twitter_screen_name":"0w0_area_XxX"},"id":"07a481921a2ac09a049f","created_at":"2018-09-22T17:38:38+09:00","title":"VSCodeでCSVをステキに見やすくする「Rainbow CSV」を紹介するよ","tags":[{"name":"CSV"},{"name":"VSCode"}],"score":"217.7"},{"rank":8,"url":"https://qiita.com/potato4d/items/13050d5934ff592dc539","user":{"profile_image_url":"https://qiita-image-store.s3.amazonaws.com/0/75633/profile-images/1536509921","id":"potato4d","twitter_screen_name":"potato4d"},"id":"13050d5934ff592dc539","created_at":"2018-09-10T12:48:20+09:00","title":"Nuxt.js, Firebase, Stripe をフル活用してサーバーレスでJAMStackなECサイトを2日で開発した話","tags":[{"name":"JavaScript"},{"name":"stripe"},{"name":"vue.js"},{"name":"Firebase"},{"name":"nuxt.js"}],"score":"199.1"},{"rank":9,"url":"https://qiita.com/yosatonet/items/2fc441343d210a484789","user":{"profile_image_url":"https://pbs.twimg.com/profile_images/798770465678376960/GG6uza9f_bigger.jpg","id":"yosatonet","twitter_screen_name":"yosatonet"},"id":"2fc441343d210a484789","created_at":"2018-09-28T01:22:08+09:00","title":"新しいExcelの一番の変更点は「スピル」？","tags":[{"name":"Excel"}],"score":"189.5"},{"rank":10,"url":"https://qiita.com/ytanaka/items/6cfad69a4c000c05be40","user":{"profile_image_url":"https://qiita-image-store.s3.amazonaws.com/0/51540/profile-images/1473692473","id":"ytanaka","twitter_screen_name":"_ytanaka_"},"id":"6cfad69a4c000c05be40","created_at":"2018-09-07T06:05:54+09:00","title":"約3年かけてプログラマ向けニュース推薦アプリを作り直した話","tags":[{"name":"アルゴリズム"},{"name":"アプリ"},{"name":"推薦システム"},{"name":"Webサービス"}],"score":"186.0"},{"rank":11,"url":"https://qiita.com/inamiy/items/922d4220bf407efa2dab","user":{"profile_image_url":"https://qiita-image-store.s3.amazonaws.com/0/2249/profile-images/1536596006","id":"inamiy","twitter_screen_name":"inamiy"},"id":"922d4220bf407efa2dab","created_at":"2018-09-10T09:19:42+09:00","title":"圏論のオススメ勉強法（プログラマ向け）","tags":[{"name":"圏論"}],"score":"171.0"},{"rank":12,"url":"https://qiita.com/tsin1rou/items/d4c781a2f25e2b92fa5e","user":{"profile_image_url":"https://pbs.twimg.com/profile_images/1025767827712561153/PE457p_G_bigger.jpg","id":"tsin1rou","twitter_screen_name":"tsin1rou"},"id":"d4c781a2f25e2b92fa5e","created_at":"2018-09-12T00:41:00+09:00","title":"実際のところ「ブラウザを立ち上げてページが表示されるまで」には何が起きるのか","tags":[{"name":"Web"},{"name":"Blink"}],"score":"161.6"},{"rank":13,"url":"https://qiita.com/neer_chan/items/2c62fee08489ce30800b","user":{"id":"neer_chan","profile_image_url":"https://qiita-image-store.s3.amazonaws.com/0/192145/profile-images/1520811206"},"id":"2c62fee08489ce30800b","created_at":"2018-09-16T17:46:29+09:00","title":"表示の遅いWebページは何も価値がない","tags":[{"name":"HTML"},{"name":"CSS"},{"name":"JavaScript"},{"name":"Web"}],"score":"146.9"},{"rank":14,"url":"https://qiita.com/shinobu_shiva/items/e0c458aa6c1e683a9881","user":{"profile_image_url":"https://qiita-image-store.s3.amazonaws.com/0/5557/profile-images/1473682084","id":"shinobu_shiva","twitter_screen_name":"shinobu_shiva"},"id":"e0c458aa6c1e683a9881","created_at":"2018-09-20T04:32:24+09:00","title":"「Vueコンサルが教えたくない７つの真実」を勉強してみた","tags":[{"name":"JavaScript"},{"name":"vue.js"}],"score":"146.3"},{"rank":15,"url":"https://qiita.com/y_kawase/items/8f1b5a303400a09c4923","user":{"profile_image_url":"https://qiita-image-store.s3.amazonaws.com/0/262161/profile-images/1535074879","id":"y_kawase","twitter_screen_name":"y_kawase"},"id":"8f1b5a303400a09c4923","created_at":"2018-09-03T11:52:27+09:00","title":"Reactで誰もがやりたかった10の機能。アプリ構想はあるけど作れない人の壁をぶっ壊す。","tags":[{"name":"SPA"},{"name":"React"},{"name":"react-router"},{"name":"redux"},{"name":"material-ui"}],"score":"140.1"},{"rank":16,"url":"https://qiita.com/Nkzn/items/326ad03e358b5d3fbafc","user":{"profile_image_url":"https://qiita-image-store.s3.amazonaws.com/0/2276/profile-images/1473681370","id":"Nkzn","twitter_screen_name":"Nkzn"},"id":"326ad03e358b5d3fbafc","created_at":"2018-09-20T11:02:23+09:00","title":"広告IDを使っている覚えがないのにGoogle Playからポリシー違反を通告されたけどFirebaseのせいだった","tags":[{"name":"Android"},{"name":"Firebase"}],"score":"114.0"},{"rank":17,"url":"https://qiita.com/sensuikan1973/items/74cf5383c02dbcd82234","user":{"profile_image_url":"https://qiita-image-store.s3.amazonaws.com/0/159680/profile-images/1490964068","id":"sensuikan1973","twitter_screen_name":"sensuikan1973"},"id":"74cf5383c02dbcd82234","created_at":"2018-09-30T14:57:40+09:00","title":"VSCodeのオススメ拡張機能 24選   (とTipsを少し)","tags":[{"name":"Git"},{"name":"VSCode"}],"score":"101.2"},{"rank":18,"url":"https://qiita.com/acro5piano/items/df53d695c84db83061da","user":{"profile_image_url":"https://qiita-image-store.s3.amazonaws.com/0/103885/profile-images/1484882017","id":"acro5piano","twitter_screen_name":"YDP140"},"id":"df53d695c84db83061da","created_at":"2018-09-19T00:10:09+09:00","title":"英語のコーディング面接 (React) を受けた感想、やっておけば良かったと思ったことなど","tags":[{"name":"JavaScript"},{"name":"英語"},{"name":"reactjs"},{"name":"キャリア"}],"score":"97.5"},{"rank":19,"url":"https://qiita.com/ishida330/items/53f1b0df2247fab5c6dd","user":{"id":"ishida330","profile_image_url":"https://qiita-image-store.s3.amazonaws.com/0/108535/profile-images/1473710583"},"id":"53f1b0df2247fab5c6dd","created_at":"2018-09-08T17:35:35+09:00","title":"Jupyter/Pythonでデータ分析する人にお勧めしたい！便利なライブラリー「PixieDust」をザクッと紹介します","tags":[{"name":"Python"},{"name":"Spark"},{"name":"pandas"},{"name":"Visualization"},{"name":"Jupyter"}],"score":"85.2"},{"rank":20,"url":"https://qiita.com/shunp/items/4289660b912d90536ece","user":{"profile_image_url":"https://avatars3.githubusercontent.com/u/24355719?v=4","id":"shunp","twitter_screen_name":"shunpei42ba_"},"id":"4289660b912d90536ece","created_at":"2018-09-08T17:56:53+09:00","title":"休日2日を生け贄に青眼の白龍を召喚！","tags":[{"name":"SpriteKit"},{"name":"Swift"},{"name":"ARKit"},{"name":"iOS12"},{"name":"青眼の白龍"}],"score":"84.2"},{"rank":21,"url":"https://qiita.com/poly_soft/items/f08460f559ed5e9304b5","user":{"profile_image_url":"https://qiita-image-store.s3.amazonaws.com/0/22932/profile-images/1473683684","id":"poly_soft","twitter_screen_name":"poly_soft"},"id":"f08460f559ed5e9304b5","created_at":"2018-09-22T14:36:45+09:00","title":"moffersで年収1200万円のオファーをゲットしたエンジニアの業務経歴を公開します","tags":[{"name":"キャリア"},{"name":"転職ドラフト"},{"name":"moffers"}],"score":"79.4"},{"rank":22,"url":"https://qiita.com/nrslib/items/a5f902c4defc83bd46b8","user":{"profile_image_url":"https://avatars0.githubusercontent.com/u/38722970?v=4","id":"nrslib","twitter_screen_name":"nrslib"},"id":"a5f902c4defc83bd46b8","created_at":"2018-09-30T00:42:41+09:00","title":"実装クリーンアーキテクチャ","tags":[{"name":"オブジェクト指向"},{"name":"設計"},{"name":"oop"},{"name":"アーキテクチャ"},{"name":"CleanArchitecture"}],"score":"77.3"},{"rank":23,"url":"https://qiita.com/Sekky0905/items/2436d669ff5d4491c527","user":{"profile_image_url":"https://avatars.githubusercontent.com/u/20237968?v=3","id":"Sekky0905","twitter_screen_name":"Sekky0905Ks"},"id":"2436d669ff5d4491c527","created_at":"2018-09-25T20:33:02+09:00","title":"その設計、変更に強いですか?単体テストできますか?...そしてクリーンアーキテクチャ ","tags":[{"name":"Go"},{"name":"golang"},{"name":"設計"},{"name":"アーキテクチャ"},{"name":"CleanArchitecture"}],"score":"73.3"},{"rank":24,"url":"https://qiita.com/Watt/items/7d865713b9575d0daedf","user":{"id":"Watt","profile_image_url":"https://qiita-image-store.s3.amazonaws.com/0/206720/profile-images/1518974470"},"id":"7d865713b9575d0daedf","created_at":"2018-09-16T02:44:55+09:00","title":"ある規約違反 iOS アプリが削除されるまでの4日間","tags":[{"name":"iOS"},{"name":"ポエム"},{"name":"ADEP"}],"score":"70.8"},{"rank":25,"url":"https://qiita.com/k_mayo_beam/items/0dd5bc768a1f8dd421fc","user":{"profile_image_url":"https://qiita-image-store.s3.amazonaws.com/0/273809/profile-images/1536389455","id":"k_mayo_beam","twitter_screen_name":"kame_m_beam"},"id":"0dd5bc768a1f8dd421fc","created_at":"2018-09-11T20:12:55+09:00","title":"Python×業務効率化 Automagicaでブラウザを自動で動かしてみた","tags":[{"name":"Python"},{"name":"業務効率化"},{"name":"automagica"}],"score":"70.1"},{"rank":26,"url":"https://qiita.com/yuji_ariyasu/items/588fef6062b3c7149509","user":{"id":"yuji_ariyasu","profile_image_url":"https://qiita-image-store.s3.amazonaws.com/0/257374/profile-images/1526362400"},"id":"588fef6062b3c7149509","created_at":"2018-09-10T10:52:19+09:00","title":"Rubyによるデザインパターンまとめ","tags":[{"name":"Ruby"},{"name":"Rails"},{"name":"オブジェクト指向"},{"name":"RubyOnRails"},{"name":"デザインパターン"}],"score":"69.2"},{"rank":27,"url":"https://qiita.com/rana_kualu/items/9b4502d229d19635ef34","user":{"profile_image_url":"https://qiita-image-store.s3.amazonaws.com/0/26088/profile-images/1473684492","id":"rana_kualu","twitter_screen_name":"rana_kualu"},"id":"9b4502d229d19635ef34","created_at":"2018-09-13T19:43:55+09:00","title":"ついにPHPにプロパティ型指定がやってくる","tags":[{"name":"PHP"},{"name":"rfc"},{"name":"PHP7"}],"score":"68.1"},{"rank":28,"url":"https://qiita.com/selfnavi/items/d68dc885b03306363289","user":{"id":"selfnavi","profile_image_url":"https://qiita-image-store.s3.amazonaws.com/0/209900/profile-images/1514039941"},"id":"d68dc885b03306363289","created_at":"2018-09-18T13:55:12+09:00","title":"徳丸先生が『安全なWebアプリケーションの作り方』第二版を語る会","tags":[{"name":"徳丸本第２版"},{"name":"安全なWebアプリケーションの作り方"}],"score":"67.1"},{"rank":29,"url":"https://qiita.com/piyo7/items/1c860f56bfaeb98bea04","user":{"profile_image_url":"https://qiita-image-store.s3.amazonaws.com/0/55208/profile-images/1481447486","id":"piyo7","twitter_screen_name":"moroha_yumekiri"},"id":"1c860f56bfaeb98bea04","created_at":"2018-09-13T12:17:43+09:00","title":"ブラックボックス化したデータ基盤を作りなおすことを決意した貴方へ","tags":[{"name":"リファクタリング"},{"name":"機械学習"},{"name":"新人プログラマ応援"},{"name":"サバイバルガイド"},{"name":"データエンジニアリング"}],"score":"62.9"},{"rank":30,"url":"https://qiita.com/turmericN/items/e248d8ac30ca5c21650e","user":{"profile_image_url":"https://qiita-image-store.s3.amazonaws.com/0/226008/profile-images/1530106434","id":"turmericN","twitter_screen_name":"naoto_7713"},"id":"e248d8ac30ca5c21650e","created_at":"2018-09-17T10:40:17+09:00","title":"フリーランスエンジニアの面談ってこんな感じ","tags":[{"name":"ポエム"},{"name":"面談"},{"name":"フリーランス"}],"score":"62.5"},{"rank":31,"url":"https://qiita.com/yossymura/items/b19d08235bdb44f06ae8","user":{"profile_image_url":"https://qiita-image-store.s3.amazonaws.com/0/280076/profile-images/1535724129","id":"yossymura","twitter_screen_name":"yossymura"},"id":"b19d08235bdb44f06ae8","created_at":"2018-09-22T00:48:00+09:00","title":"あなたを死なせないためのプログラミング","tags":[{"name":"Python"},{"name":"PDF"},{"name":"位置情報"},{"name":"pandas"},{"name":"LINEmessagingAPI"}],"score":"61.9"},{"rank":32,"url":"https://qiita.com/marty-suzuki/items/7c7ecdcb1f16c21b0051","user":{"profile_image_url":"https://qiita-image-store.s3.amazonaws.com/0/60325/profile-images/1473695196","id":"marty-suzuki","twitter_screen_name":"marty_suzuki"},"id":"7c7ecdcb1f16c21b0051","created_at":"2018-09-07T17:33:46+09:00","title":"XIBからViewを生成する4つの実装パターン","tags":[{"name":"iOS"},{"name":"xib"},{"name":"Swift"}],"score":"60.3"},{"rank":33,"url":"https://qiita.com/noplan1989/items/f42e2f03663b00b5886d","user":{"id":"noplan1989","profile_image_url":"https://qiita-image-store.s3.amazonaws.com/0/89103/profile-images/1473704646"},"id":"f42e2f03663b00b5886d","created_at":"2018-09-17T20:15:21+09:00","title":"Nuxt.jsの静的化に魅せられて","tags":[{"name":"JavaScript"},{"name":"vue.js"},{"name":"nuxt.js"}],"score":"60.2"},{"rank":34,"url":"https://qiita.com/otakumesi/items/9dc8dbb1b66dd3e412f2","user":{"profile_image_url":"https://qiita-image-store.s3.amazonaws.com/0/97363/profile-images/1473707175","id":"otakumesi","twitter_screen_name":"otakumesi"},"id":"9dc8dbb1b66dd3e412f2","created_at":"2018-09-06T09:07:04+09:00","title":"SEO対策をサーバーサイドレンダリングせずにやっていく","tags":[{"name":"JavaScript"},{"name":"SEO"},{"name":"SPA"},{"name":"frontend"},{"name":"babel"}],"score":"59.8"},{"rank":35,"url":"https://qiita.com/Mister_K/items/6b9bd54d6226e260c308","user":{"id":"Mister_K","profile_image_url":"https://qiita-image-store.s3.amazonaws.com/0/269942/profile-images/1535100910"},"id":"6b9bd54d6226e260c308","created_at":"2018-09-26T10:35:19+09:00","title":"UIデザインは人の好奇心に依存している","tags":[{"name":"UX"},{"name":"UI"},{"name":"UXデザイン関連"},{"name":"UIデザイン"}],"score":"58.9"},{"rank":36,"url":"https://qiita.com/inamiy/items/c4e85f22273e98b8db26","user":{"profile_image_url":"https://qiita-image-store.s3.amazonaws.com/0/2249/profile-images/1536596006","id":"inamiy","twitter_screen_name":"inamiy"},"id":"c4e85f22273e98b8db26","created_at":"2018-09-06T08:48:35+09:00","title":"iOSDC Japan 2018 で発表した「圏論とSwiftへの応用」の補足","tags":[{"name":"Haskell"},{"name":"iOS"},{"name":"圏論"},{"name":"Swift"},{"name":"iOSDC"}],"score":"58.3"},{"rank":37,"url":"https://qiita.com/hibit/items/9a1d16a3c24061c27af3","user":{"profile_image_url":"https://pbs.twimg.com/profile_images/1469073733/_____bigger.jpg","id":"hibit","twitter_screen_name":"hibit_at"},"id":"9a1d16a3c24061c27af3","created_at":"2018-09-27T16:36:05+09:00","title":"1行で描けるかんたんシェーダ5点盛り","tags":[{"name":"Unity"},{"name":"Shader"}],"score":"54.3"},{"rank":38,"url":"https://qiita.com/noplan1989/items/eae57372e2fd360438e0","user":{"id":"noplan1989","profile_image_url":"https://qiita-image-store.s3.amazonaws.com/0/89103/profile-images/1473704646"},"id":"eae57372e2fd360438e0","created_at":"2018-09-03T10:43:57+09:00","title":"Vue.jsとNuxt.jsを使っていて、どっちのドキュメントを見ればいいんだ？ってなったときのために、それぞれの機能を整理する。","tags":[{"name":"JavaScript"},{"name":"vue.js"},{"name":"nuxt.js"}],"score":"51.9"},{"rank":39,"url":"https://qiita.com/gorilla0513/items/814f369bb25b1ea3ae00","user":{"id":"gorilla0513","profile_image_url":"https://qiita-image-store.s3.amazonaws.com/0/66178/profile-images/1533568770"},"id":"814f369bb25b1ea3ae00","created_at":"2018-09-24T15:58:46+09:00","title":"Goで直感的に簡単にdockerを操作できるCUIツールを作りました","tags":[{"name":"Go"},{"name":"GUI"},{"name":"CUI"},{"name":"docker"},{"name":"gocui"}],"score":"50.1"},{"rank":40,"url":"https://qiita.com/lufia/items/242d25e8c93d88e22a2e","user":{"id":"lufia","profile_image_url":"https://qiita-image-store.s3.amazonaws.com/0/31421/profile-images/1473685690"},"id":"242d25e8c93d88e22a2e","created_at":"2018-09-19T02:28:09+09:00","title":"Go 2のgenerics/contract簡易まとめ","tags":[{"name":"Go"}],"score":"49.2"},{"rank":41,"url":"https://qiita.com/unecochan/items/ac206365745257d68926","user":{"profile_image_url":"https://qiita-image-store.s3.amazonaws.com/0/1023/profile-images/1538355065","id":"unecochan","twitter_screen_name":"unecochan"},"id":"ac206365745257d68926","created_at":"2018-10-01T09:49:03+09:00","title":"[和訳] 次期 Vue (v3.0) の計画 / Plans for the Next Iteration of Vue.js","tags":[{"name":"vue.js"}],"score":"48.2"},{"rank":42,"url":"https://qiita.com/yuzooho/items/259b93bd4d445f81616d","user":{"profile_image_url":"https://qiita-image-store.s3.amazonaws.com/0/97496/profile-images/1535077386","id":"yuzooho","twitter_screen_name":"yuzooho"},"id":"259b93bd4d445f81616d","created_at":"2018-09-30T00:29:28+09:00","title":"WebサービスにおけるCSS再設計で考えたこと","tags":[{"name":"CSS"},{"name":"CSS設計"}],"score":"43.6"},{"rank":43,"url":"https://qiita.com/_kanacan_/items/59f3959169c41a167b1e","user":{"profile_image_url":"https://qiita-image-store.s3.amazonaws.com/0/254083/profile-images/1536309315","id":"_kanacan_","twitter_screen_name":"_kanacan_"},"id":"59f3959169c41a167b1e","created_at":"2018-09-11T00:03:02+09:00","title":"30分でできるRuby on RailsとGitHubやエディタまわりの環境構築","tags":[{"name":"Ruby"},{"name":"Rails"},{"name":"GitHub"},{"name":"環境構築"},{"name":"ターミナル"}],"score":"43.1"},{"rank":44,"url":"https://qiita.com/Azunyan1111/items/a1964c18e409fe6718fd","user":{"id":"Azunyan1111","profile_image_url":"https://qiita-image-store.s3.amazonaws.com/0/110135/profile-images/1535776100"},"id":"a1964c18e409fe6718fd","created_at":"2018-09-13T09:25:49+09:00","title":"Webスクレイピングマスターが教える「スクレイピング対策」","tags":[{"name":"HTML"},{"name":"CSS"},{"name":"WordPress"},{"name":"Selenium"},{"name":"スクレイピング"}],"score":"40.8"},{"rank":45,"url":"https://qiita.com/isihigameKoudai/items/e3b136e9964f1d30d73d","user":{"id":"isihigameKoudai","profile_image_url":"https://qiita-image-store.s3.amazonaws.com/0/105049/profile-images/1516018105"},"id":"e3b136e9964f1d30d73d","created_at":"2018-09-27T03:15:09+09:00","title":"Nuxt.js + Netlifyで爆速構築するサーバーレスSPA開発入門","tags":[{"name":"JavaScript"},{"name":"vue.js"},{"name":"frontend"},{"name":"serverless"},{"name":"nuxt.js"}],"score":"40.3"},{"rank":46,"url":"https://qiita.com/kai_kou/items/19b494a41023d84bacc7","user":{"profile_image_url":"https://qiita-image-store.s3.amazonaws.com/0/48549/profile-images/1524132209","id":"kai_kou","twitter_screen_name":"k_aik_ou"},"id":"19b494a41023d84bacc7","created_at":"2018-09-10T08:35:28+09:00","title":"Vue.js+TypeScriptで開発するときの参考記事まとめ","tags":[{"name":"TypeScript"},{"name":"unittest"},{"name":"まとめ"},{"name":"vue.js"},{"name":"Vuex"}],"score":"39.3"},{"rank":47,"url":"https://qiita.com/uhyo/items/ab8e273e1eb71d02e29a","user":{"profile_image_url":"https://qiita-image-store.s3.amazonaws.com/0/233667/profile-images/1516890571","id":"uhyo","twitter_screen_name":"uhyo_"},"id":"ab8e273e1eb71d02e29a","created_at":"2018-09-26T00:17:36+09:00","title":"JavaScriptのオブジェクト指向が10%理解できる記事（実践編）","tags":[{"name":"JavaScript"},{"name":"オブジェクト指向"}],"score":"38.9"},{"rank":48,"url":"https://qiita.com/tu-kun/items/d38452161bfb9da54bcd","user":{"profile_image_url":"https://qiita-image-store.s3.amazonaws.com/0/248805/profile-images/1527926726","id":"tu-kun","twitter_screen_name":"tu_kun_0220"},"id":"d38452161bfb9da54bcd","created_at":"2018-09-25T00:01:33+09:00","title":"AWSにsshログインした時にスライムを出現するようにしてみた。","tags":[{"name":"AWS"},{"name":"EC2"},{"name":"環境構築"},{"name":"motd"}],"score":"36.5"},{"rank":49,"url":"https://qiita.com/neet_se/items/1740f5fde60cb9c06e5f","user":{"profile_image_url":"https://qiita-image-store.s3.amazonaws.com/0/148071/profile-images/1537763646","id":"neet_se","twitter_screen_name":"neet_se"},"id":"1740f5fde60cb9c06e5f","created_at":"2018-09-24T13:35:16+09:00","title":"アラサー未経験からのIT転職","tags":[{"name":"転職"},{"name":"未経験エンジニア"},{"name":"アラサー"}],"score":"35.2"},{"rank":50,"url":"https://qiita.com/turmericN/items/a73d005e8bf4700bbb37","user":{"profile_image_url":"https://qiita-image-store.s3.amazonaws.com/0/226008/profile-images/1530106434","id":"turmericN","twitter_screen_name":"naoto_7713"},"id":"a73d005e8bf4700bbb37","created_at":"2018-09-03T23:31:06+09:00","title":"25歳初めてのフリーランスエンジニアの単価について","tags":[{"name":"ポエム"},{"name":"キャリア"},{"name":"フリーランス"}],"score":"34.8"}]