[{"user":{"id":"omochimetaru","twitter_screen_name":"omochimetaru","profile_image_url":"https://qiita-image-store.s3.amazonaws.com/0/20130/profile-images/1473682917"},"score":"144.5","id":"c95e0d36ae7f1b1a9052","created_at":"2017-01-21T01:25:51+09:00","title":"素晴らしいSwiftのポインタ型の解説","rank":1,"tags":[{"name":"C"},{"name":"C++"},{"name":"Swift"}],"url":"http://qiita.com/omochimetaru/items/c95e0d36ae7f1b1a9052"},{"user":{"id":"AQRiL_1132","twitter_screen_name":"AQRiL_1132","profile_image_url":"https://qiita-image-store.s3.amazonaws.com/0/103957/profile-images/1483768234"},"score":"71.8","id":"c185c7ad84c129e5a2df","created_at":"2017-01-20T01:45:03+09:00","title":"正規表現チェックツールまとめ","rank":2,"tags":[{"name":"Java"},{"name":"Python"},{"name":"JavaScript"},{"name":"正規表現"},{"name":"regexp"}],"url":"http://qiita.com/AQRiL_1132/items/c185c7ad84c129e5a2df"},{"user":{"id":"shiozaki","profile_image_url":"https://qiita-image-store.s3.amazonaws.com/0/74551/profile-images/1473699875"},"score":"60.9","id":"0e42e101b7483df13c8f","created_at":"2017-01-20T12:30:33+09:00","title":"✨安い！！お得！！激安CSS！！✨","rank":3,"tags":[{"name":"HTML"},{"name":"CSS"},{"name":"HTML5"},{"name":"CSS3"},{"name":"デザイン"}],"url":"http://qiita.com/shiozaki/items/0e42e101b7483df13c8f"},{"user":{"id":"mizchi","twitter_screen_name":"mizchi","profile_image_url":"https://qiita-image-store.s3.amazonaws.com/0/1727/profile-images/1473683814"},"score":"59.3","id":"8cf4e0c868f5c49ebcbf","created_at":"2017-01-23T17:27:34+09:00","title":"「後付の型システム」の活用についてFlowtypeとReduxから考える","rank":4,"tags":[{"name":"flowtype"},{"name":"redux"}],"url":"http://qiita.com/mizchi/items/8cf4e0c868f5c49ebcbf"},{"user":{"id":"omochimetaru","twitter_screen_name":"omochimetaru","profile_image_url":"https://qiita-image-store.s3.amazonaws.com/0/20130/profile-images/1473682917"},"score":"55.6","id":"64b073c5d6bcf1bbbf99","created_at":"2017-01-21T22:48:24+09:00","title":"Swiftのメモリレイアウトを調べる","rank":5,"tags":[{"name":"Swift"}],"url":"http://qiita.com/omochimetaru/items/64b073c5d6bcf1bbbf99"},{"user":{"id":"toRisouP","twitter_screen_name":"toRisouP","profile_image_url":"https://qiita-image-store.s3.amazonaws.com/0/47146/profile-images/1473690888"},"score":"48.7","id":"5b7814fda00cab120e39","created_at":"2017-01-25T02:13:04+09:00","title":"グローバルゲームジャムでクラス設計をやった話2017","rank":6,"tags":[{"name":"Unity"},{"name":"plantuml"},{"name":"gamejam"},{"name":"UniRx"}],"url":"http://qiita.com/toRisouP/items/5b7814fda00cab120e39"},{"user":{"id":"omochimetaru","twitter_screen_name":"omochimetaru","profile_image_url":"https://qiita-image-store.s3.amazonaws.com/0/20130/profile-images/1473682917"},"score":"46.6","id":"991b5e3d9a0c713a628e","created_at":"2017-01-22T22:21:51+09:00","title":"Swiftのenumのメモリレイアウトの最適化が凄い","rank":7,"tags":[{"name":"Swift"}],"url":"http://qiita.com/omochimetaru/items/991b5e3d9a0c713a628e"},{"user":{"id":"boiyaa","profile_image_url":"https://avatars.githubusercontent.com/u/12344093?v=3"},"score":"40.5","id":"20a4fd0cc79f7d3b4a56","created_at":"2017-01-22T23:25:52+09:00","title":"GitHub/CircleCI/SlackをまとめてクローンしたようなOSS、Omnibus GitLabでモダンな開発環境を一気に構築","rank":8,"tags":[{"name":"GitHub"},{"name":"GitLab"},{"name":"docker"},{"name":"Slack"},{"name":"Mattermost"}],"url":"http://qiita.com/boiyaa/items/20a4fd0cc79f7d3b4a56"},{"user":{"id":"yuyake0084","twitter_screen_name":"yuyake0084LL","profile_image_url":"https://qiita-image-store.s3.amazonaws.com/0/88810/profile-images/1482374713"},"score":"35.0","id":"3c901f37ed7333d4da16","created_at":"2017-01-19T19:01:30+09:00","title":"ES2016 / ES2017の最新動向を追ってみた","rank":9,"tags":[{"name":"JavaScript"},{"name":"ECMAScript"},{"name":"es2016"},{"name":"es2017"}],"url":"http://qiita.com/yuyake0084/items/3c901f37ed7333d4da16"},{"user":{"id":"hiroshitoda","twitter_screen_name":"hiroshitoda","profile_image_url":"https://qiita-image-store.s3.amazonaws.com/0/33963/profile-images/1473686235"},"score":"34.5","id":"ed2b0a89ace2db2e1847","created_at":"2017-01-22T16:43:35+09:00","title":"Selenium禁止","rank":10,"tags":[{"name":"Selenium"},{"name":"スクレイピング"},{"name":"selenium-webdriver"}],"url":"http://qiita.com/hiroshitoda/items/ed2b0a89ace2db2e1847"},{"user":{"id":"knhr__","twitter_screen_name":"knhr__","profile_image_url":"https://qiita-image-store.s3.amazonaws.com/0/134294/profile-images/1473719243"},"score":"33.1","id":"6c414aaaa441cc3a90c7","created_at":"2017-01-18T22:44:03+09:00","title":"謎だったJavaScriptのコードたち","rank":11,"tags":[{"name":"JavaScript"},{"name":"es2015"}],"url":"http://qiita.com/knhr__/items/6c414aaaa441cc3a90c7"},{"user":{"id":"HajimeKawahara","profile_image_url":"https://qiita-image-store.s3.amazonaws.com/0/137970/profile-images/1473720452"},"score":"28.6","id":"03f29367744d5209be42","created_at":"2017-01-18T22:21:51+09:00","title":"matplotlibでジャーナルに投稿可能な図を作るためのメモ","rank":12,"tags":[{"name":"Python"},{"name":"matplotlib"}],"url":"http://qiita.com/HajimeKawahara/items/03f29367744d5209be42"},{"user":{"id":"0829","profile_image_url":"https://qiita-image-store.s3.amazonaws.com/0/14471/profile-images/1484921592"},"score":"26.6","id":"c1e494bb128ade5f0872","created_at":"2017-01-20T22:34:28+09:00","title":"Goではじめてみたブラウザの自動操作","rank":13,"tags":[{"name":"Go"},{"name":"Selenium"},{"name":"Xvfb"},{"name":"docker"}],"url":"http://qiita.com/0829/items/c1e494bb128ade5f0872"},{"user":{"id":"q-ikawa","profile_image_url":"https://avatars.githubusercontent.com/u/19247322?v=3"},"score":"20.0","id":"3f55089e9081e1a854bc","created_at":"2017-01-18T23:03:19+09:00","title":"Java8のStreamやOptionalでクールに例外を処理する方法","rank":14,"tags":[{"name":"Java"},{"name":"ラムダ式"},{"name":"java8"}],"url":"http://qiita.com/q-ikawa/items/3f55089e9081e1a854bc"},{"user":{"id":"woxtu","twitter_screen_name":"woxtu","profile_image_url":"https://qiita-image-store.s3.amazonaws.com/0/4250/profile-images/1473683866"},"score":"18.1","id":"93c5bcf48c31fef5b300","created_at":"2017-01-24T02:58:05+09:00","title":"bashの組み込みコマンドをつくる","rank":15,"tags":[{"name":"rust"}],"url":"http://qiita.com/woxtu/items/93c5bcf48c31fef5b300"},{"user":{"id":"seigok","profile_image_url":"https://qiita-image-store.s3.amazonaws.com/0/86998/profile-images/1473703933"},"score":"16.4","id":"b74c722d9ad60c9b2efd","created_at":"2017-01-24T22:05:32+09:00","title":"【技術翻訳】モノリシック・プラットフォームが時代遅れな２５の理由","rank":16,"tags":[{"name":"devops"},{"name":"microservices"},{"name":"マイクロサービス"}],"url":"http://qiita.com/seigok/items/b74c722d9ad60c9b2efd"},{"user":{"id":"niku","twitter_screen_name":"niku_name","profile_image_url":"https://qiita-image-store.s3.amazonaws.com/0/20546/profile-images/1473683046"},"score":"16.0","id":"51f0389a0f7b8db64c01","created_at":"2017-01-20T13:18:14+09:00","title":"Elixirでコマンド実行可能なスクリプトを書きGistで配布する","rank":17,"tags":[{"name":"gist"},{"name":"Elixir"}],"url":"http://qiita.com/niku/items/51f0389a0f7b8db64c01"},{"user":{"id":"DaisukeKondo","profile_image_url":"https://qiita-image-store.s3.amazonaws.com/0/38837/profile-images/1473687900"},"score":"15.4","id":"e160318083fa7cc2fb2b","created_at":"2017-01-23T04:43:07+09:00","title":"アニメの視聴傾向を比較するツールを作ってみた","rank":18,"tags":[{"name":"Node.js"},{"name":"d3.js"},{"name":"Nightmare"},{"name":"Annict"},{"name":"Venn.js"}],"url":"http://qiita.com/DaisukeKondo/items/e160318083fa7cc2fb2b"},{"user":{"id":"sion_cojp","twitter_screen_name":"sion_cojp","profile_image_url":"https://qiita-image-store.s3.amazonaws.com/0/29405/profile-images/1473685334"},"score":"15.4","id":"2776728918ec3d2dad10","created_at":"2017-01-23T01:29:35+09:00","title":"commit番号毎で、URLにアクセス出来るgalaxyというAPIを作った","rank":19,"tags":[{"name":"Go"},{"name":"docker"}],"url":"http://qiita.com/sion_cojp/items/2776728918ec3d2dad10"},{"user":{"id":"jiny2001","twitter_screen_name":"Jiny2001","profile_image_url":"https://avatars.githubusercontent.com/u/12959344?v=3"},"score":"14.6","id":"1d3f2d0370b2689d2da7","created_at":"2017-01-23T15:16:27+09:00","title":"Inside of Deep Learning （ディープラーニングの性能改善手法 一覧）","rank":20,"tags":[{"name":"DeepLearning"},{"name":"深層学習"}],"url":"http://qiita.com/jiny2001/items/1d3f2d0370b2689d2da7"},{"user":{"id":"jiny2001","twitter_screen_name":"Jiny2001","profile_image_url":"https://avatars.githubusercontent.com/u/12959344?v=3"},"score":"12.8","id":"ee816b442e1ee8ed7a5c","created_at":"2017-01-22T17:00:45+09:00","title":"ディープラーニングによる超解像(Deeply-Recursive Convolutional Network)のtensorflow実装","rank":21,"tags":[{"name":"DeepLearning"},{"name":"深層学習"},{"name":"TensorFlow"}],"url":"http://qiita.com/jiny2001/items/ee816b442e1ee8ed7a5c"},{"user":{"id":"hikarut","profile_image_url":"https://qiita-image-store.s3.amazonaws.com/0/110485/profile-images/1474383172"},"score":"12.5","id":"c7a0e45a962b16c7907a","created_at":"2017-01-21T16:47:34+09:00","title":"【初心者向け】MacでDockerを使ってTensorFlowの画像認識を試す","rank":22,"tags":[{"name":"機械学習"},{"name":"docker"},{"name":"ディープラーニング"},{"name":"TensorFlow"}],"url":"http://qiita.com/hikarut/items/c7a0e45a962b16c7907a"},{"user":{"id":"Hironsan","twitter_screen_name":"Hironsan13","profile_image_url":"https://qiita-image-store.s3.amazonaws.com/0/77079/profile-images/1473700709"},"score":"12.1","id":"8f7d35f0a36e0f99752c","created_at":"2017-01-20T12:43:37+09:00","title":"いますぐ使える単語埋め込みベクトルのリスト","rank":23,"tags":[{"name":"Python"},{"name":"自然言語処理"},{"name":"機械学習"},{"name":"DeepLearning"},{"name":"gensim"}],"url":"http://qiita.com/Hironsan/items/8f7d35f0a36e0f99752c"},{"user":{"id":"zenno04","twitter_screen_name":"Zenno004","profile_image_url":"https://qiita-image-store.s3.amazonaws.com/0/56303/profile-images/1473693959"},"score":"10.8","id":"e374c6b8d6a1d12dd0b2","created_at":"2017-01-22T13:46:44+09:00","title":"文系人間のJava再入門: プログラミングという行為に対する理解","rank":24,"tags":[{"name":"Java"},{"name":"ポエム"},{"name":"HelloWorld"}],"url":"http://qiita.com/zenno04/items/e374c6b8d6a1d12dd0b2"},{"user":{"id":"marty-suzuki","twitter_screen_name":"marty_suzuki","profile_image_url":"https://qiita-image-store.s3.amazonaws.com/0/60325/profile-images/1473695196"},"score":"10.3","id":"496f211e22cad1f8de19","created_at":"2017-01-22T20:19:11+09:00","title":"DispatchQueueでthrottle/debounceを実現する","rank":25,"tags":[{"name":"Swift"},{"name":"Swift3.0"}],"url":"http://qiita.com/marty-suzuki/items/496f211e22cad1f8de19"},{"user":{"id":"short-clawed_otter","profile_image_url":"https://qiita-image-store.s3.amazonaws.com/0/94135/profile-images/1473706177"},"score":"9.4","id":"e006dd4892e4e28cdef6","created_at":"2017-01-21T21:07:57+09:00","title":" ゆるふわ強化学習1","rank":26,"tags":[{"name":"機械学習"},{"name":"強化学習"},{"name":"機械学習入門"}],"url":"http://qiita.com/short-clawed_otter/items/e006dd4892e4e28cdef6"},{"user":{"id":"ksyunnnn","twitter_screen_name":"ksyunnnn","profile_image_url":"https://qiita-image-store.s3.amazonaws.com/0/117615/profile-images/1473899418"},"score":"8.3","id":"0f3a84706d4da21f687e","created_at":"2017-01-19T02:27:14+09:00","title":"これからエンジニアとかウェブデザイナーになりたい人に役に立ちたい無料の学習教材一覧","rank":27,"tags":[{"name":"HTML"},{"name":"CSS"},{"name":"JavaScript"},{"name":"Rails"},{"name":"tool"}],"url":"http://qiita.com/ksyunnnn/items/0f3a84706d4da21f687e"},{"user":{"id":"akiraak","profile_image_url":"https://qiita-image-store.s3.amazonaws.com/0/33704/profile-images/1473686182"},"score":"8.2","id":"870173a361a59f1e88bb","created_at":"2017-01-22T10:43:10+09:00","title":"畳み込み層とプーリング層を画像表示してみるてすと","rank":28,"tags":[{"name":"DeepLearning"},{"name":"可視化"},{"name":"CNN"},{"name":"TensorFlow"}],"url":"http://qiita.com/akiraak/items/870173a361a59f1e88bb"},{"user":{"id":"scrtree","twitter_screen_name":"scrtree","profile_image_url":"https://qiita-image-store.s3.amazonaws.com/0/18207/profile-images/1473682371"},"score":"6.8","id":"4686500cb3c3eb193845","created_at":"2017-01-19T07:36:41+09:00","title":"Macの標準アプリ「プレビュー.app」はエンジニアとデザイナーの架け橋","rank":29,"tags":[{"name":"Mac"},{"name":"Design"},{"name":"tips"},{"name":"apple"},{"name":"Preview"}],"url":"http://qiita.com/scrtree/items/4686500cb3c3eb193845"},{"user":{"id":"akatsuki174","twitter_screen_name":"akatsuki174","profile_image_url":"https://qiita-image-store.s3.amazonaws.com/0/100736/profile-images/1473708190"},"score":"6.4","id":"748f1cb367bbfc196502","created_at":"2017-01-21T20:52:31+09:00","title":"今更だけど独自クラスでQuick Lookを使う方法について調べた","rank":30,"tags":[{"name":"Xcode"},{"name":"iOS"},{"name":"Swift"}],"url":"http://qiita.com/akatsuki174/items/748f1cb367bbfc196502"}]