[{"user":{"id":"toRisouP","twitter_screen_name":"toRisouP","profile_image_url":"https://qiita-image-store.s3.amazonaws.com/0/47146/profile-images/1473690888"},"score":"115.0","id":"5b7814fda00cab120e39","created_at":"2017-01-25T02:13:04+09:00","title":"グローバルゲームジャムでクラス設計をやった話2017","rank":1,"tags":[{"name":"Unity"},{"name":"plantuml"},{"name":"gamejam"},{"name":"UniRx"}],"url":"http://qiita.com/toRisouP/items/5b7814fda00cab120e39"},{"user":{"id":"taizan","profile_image_url":"https://qiita-image-store.s3.amazonaws.com/0/61566/profile-images/1482641346"},"score":"86.7","id":"7119e16064cc11500f32","created_at":"2017-01-27T18:42:56+09:00","title":"chainerで線画着色をwebサービスにして公開してみた","rank":2,"tags":[{"name":"Python"},{"name":"DeepLearning"},{"name":"Chainer"}],"url":"http://qiita.com/taizan/items/7119e16064cc11500f32"},{"user":{"id":"notargs","twitter_screen_name":"notargs","profile_image_url":"https://qiita-image-store.s3.amazonaws.com/0/52576/profile-images/1484905788"},"score":"61.6","id":"be2fa153e62e3554a773","created_at":"2017-01-25T20:17:14+09:00","title":"GLSL作曲入門","rank":3,"tags":[{"name":"C++"},{"name":"GLSL"},{"name":"Shader"},{"name":"shadertoy"},{"name":"DTM"}],"url":"http://qiita.com/notargs/items/be2fa153e62e3554a773"},{"user":{"id":"kyoyababa","profile_image_url":"https://qiita-image-store.s3.amazonaws.com/0/105252/profile-images/1473709559"},"score":"54.0","id":"b7403f6ed982fefb6045","created_at":"2017-01-25T01:01:58+09:00","title":"CSSのgradient指定について知っておいたらドヤ顏できる（かもしれない）５つのこと","rank":4,"tags":[{"name":"CSS"},{"name":"CSS3"},{"name":"Sass"},{"name":"scss"},{"name":"フロントエンド"}],"url":"http://qiita.com/kyoyababa/items/b7403f6ed982fefb6045"},{"user":{"id":"mshrwtnb","profile_image_url":"https://qiita-image-store.s3.amazonaws.com/0/119686/profile-images/1473714336"},"score":"38.6","id":"8fd60ba3a8bc89f3c013","created_at":"2017-01-26T23:33:32+09:00","title":"【Swift】AppStoreのレビューフォームを開くパラメーターが新登場 - action=write-review - ","rank":5,"tags":[{"name":"iPhone"},{"name":"Xcode"},{"name":"iOS"},{"name":"AppStore"},{"name":"Swift"}],"url":"http://qiita.com/mshrwtnb/items/8fd60ba3a8bc89f3c013"},{"user":{"id":"icoxfog417","twitter_screen_name":"icoxfog417","profile_image_url":"https://qiita-image-store.s3.amazonaws.com/0/25990/profile-images/1484303516"},"score":"33.4","id":"59893813cb5bdb66a47a","created_at":"2017-01-26T13:38:25+09:00","title":"人工知能関連ニュースの、実際のところシリーズ","rank":6,"tags":[{"name":"自然言語処理"},{"name":"機械学習"}],"url":"http://qiita.com/icoxfog417/items/59893813cb5bdb66a47a"},{"user":{"id":"osyoyu","twitter_screen_name":"0x_osyoyu","profile_image_url":"https://qiita-image-store.s3.amazonaws.com/0/58426/profile-images/1473694632"},"score":"31.0","id":"a039b7e05abc6e97fb25","created_at":"2017-01-28T12:50:29+09:00","title":"Dockerで作る最強の開発環境2017","rank":7,"tags":[{"name":"docker"},{"name":"docker-compose"}],"url":"http://qiita.com/osyoyu/items/a039b7e05abc6e97fb25"},{"user":{"id":"kai-zoa","profile_image_url":"https://qiita-image-store.s3.amazonaws.com/0/27339/profile-images/1473684985"},"score":"26.6","id":"464471b71c682dd3bb83","created_at":"2017-01-29T01:11:05+09:00","title":"Goでビルドが遅くなってきたらやってること","rank":8,"tags":[{"name":"Go"},{"name":"golang"}],"url":"http://qiita.com/kai-zoa/items/464471b71c682dd3bb83"},{"user":{"id":"makomori_q","profile_image_url":"https://qiita-image-store.s3.amazonaws.com/0/62625/profile-images/1484018143"},"score":"26.5","id":"dc31788d2a8a854b1ad6","created_at":"2017-01-31T01:06:10+09:00","title":"iOSのMetal Performance Shadersでニューラルネットを実行する際のモデルの渡し方","rank":9,"tags":[{"name":"iOS"},{"name":"Metal"},{"name":"機械学習"},{"name":"DeepLearning"},{"name":"Swift"}],"url":"http://qiita.com/makomori_q/items/dc31788d2a8a854b1ad6"},{"user":{"id":"tabbyz","profile_image_url":"https://qiita-image-store.s3.amazonaws.com/0/43533/profile-images/1473689561"},"score":"21.6","id":"5f6cec37e1d525a8e4d5","created_at":"2017-01-30T08:43:00+09:00","title":"OSSなリモートスマホサービス（STF）が素敵すぎる","rank":10,"tags":[{"name":"Android"},{"name":"テスト"},{"name":"OSS"},{"name":"STF"}],"url":"http://qiita.com/tabbyz/items/5f6cec37e1d525a8e4d5"},{"user":{"id":"Nkzn","twitter_screen_name":"Nkzn","profile_image_url":"https://qiita-image-store.s3.amazonaws.com/0/2276/profile-images/1473681370"},"score":"20.6","id":"71222537f05f19681492","created_at":"2017-01-28T22:28:38+09:00","title":"あなたのAndroidアプリをInstant Appsに対応させる6つの手順","rank":11,"tags":[{"name":"Android"}],"url":"http://qiita.com/Nkzn/items/71222537f05f19681492"},{"user":{"id":"okamu_","twitter_screen_name":"okaignishon","profile_image_url":"https://qiita-image-store.s3.amazonaws.com/0/62822/profile-images/1473696084"},"score":"18.8","id":"1c8e5fde742ca165fa12","created_at":"2017-01-30T02:16:08+09:00","title":"【Docker】これは役に立つ!! docker-compose.ymlの例まとめ","rank":12,"tags":[{"name":"docker"},{"name":"docker-compose"},{"name":"rancher"}],"url":"http://qiita.com/okamu_/items/1c8e5fde742ca165fa12"},{"user":{"id":"kijibato","profile_image_url":"https://qiita-image-store.s3.amazonaws.com/0/95528/profile-images/1473706597"},"score":"15.7","id":"14ce83665505adb3addc","created_at":"2017-01-27T23:36:25+09:00","title":"サーバ・インフラ構築を効率化するためのツール一覧（目的別）","rank":13,"tags":[{"name":"AWS"},{"name":"サーバ"},{"name":"Puppet"},{"name":"docker"},{"name":"インフラ"}],"url":"http://qiita.com/kijibato/items/14ce83665505adb3addc"},{"user":{"id":"uzuki_aoba","twitter_screen_name":"uzuki_aoba","profile_image_url":"https://qiita-image-store.s3.amazonaws.com/0/52410/profile-images/1473692722"},"score":"13.4","id":"76e59f65cb50ef020e3c","created_at":"2017-01-27T20:00:58+09:00","title":"ソースコード管理(git)の説明資料を作るのに gitgraph.js を使ってみた","rank":14,"tags":[{"name":"JavaScript"},{"name":"Git"},{"name":"ドキュメンテーション"}],"url":"http://qiita.com/uzuki_aoba/items/76e59f65cb50ef020e3c"},{"user":{"id":"bohemian916","profile_image_url":"https://qiita-image-store.s3.amazonaws.com/0/50474/profile-images/1473692117"},"score":"12.6","id":"9f1e053bf73724fe0b1e","created_at":"2017-01-30T17:55:47+09:00","title":"趣味用に安く深層学習PCを作った","rank":15,"tags":[{"name":"機械学習"},{"name":"DeepLearning"},{"name":"深層学習"}],"url":"http://qiita.com/bohemian916/items/9f1e053bf73724fe0b1e"},{"user":{"id":"frost_star","twitter_screen_name":"frost_star","profile_image_url":"https://qiita-image-store.s3.amazonaws.com/0/115996/profile-images/1473713105"},"score":"12.3","id":"21de02ce0d77a156f53d","created_at":"2017-01-29T11:04:22+09:00","title":"機械学習ざっくりまとめ～パーセプトロンからディープラーニングまで～","rank":16,"tags":[{"name":"機械学習"},{"name":"DeepLearning"},{"name":"パーセプトロン"}],"url":"http://qiita.com/frost_star/items/21de02ce0d77a156f53d"},{"user":{"id":"mshrwtnb","profile_image_url":"https://qiita-image-store.s3.amazonaws.com/0/119686/profile-images/1473714336"},"score":"12.2","id":"6b9b7e9850f02f43e254","created_at":"2017-01-26T08:17:28+09:00","title":"<Swift> iOS 10.3からアプリ内レーティングが可能に！- SKStoreReviewController - ","rank":17,"tags":[{"name":"iPhone"},{"name":"Xcode"},{"name":"iOS"},{"name":"StoreKit"},{"name":"Swift"}],"url":"http://qiita.com/mshrwtnb/items/6b9b7e9850f02f43e254"},{"user":{"id":"tsuruchika","twitter_screen_name":"STRIKER_00","profile_image_url":"https://qiita-image-store.s3.amazonaws.com/0/26911/profile-images/1473684733"},"score":"10.5","id":"82fa698de7963bcf4bf2","created_at":"2017-01-30T01:56:42+09:00","title":"子供が産まれたから「おうちハック」してみた","rank":18,"tags":[{"name":"Hubot"},{"name":"RaspberryPi"},{"name":"Slack"},{"name":"おうちハック"},{"name":"Swift3.0"}],"url":"http://qiita.com/tsuruchika/items/82fa698de7963bcf4bf2"},{"user":{"id":"katsu1110","profile_image_url":"https://qiita-image-store.s3.amazonaws.com/0/122354/profile-images/1479062803"},"score":"9.8","id":"423fc9ac567710a1bd9b","created_at":"2017-01-28T22:10:03+09:00","title":"数学の苦手なバイオの学生がCourseraの機械学習コースを修了して気づいたこと","rank":19,"tags":[{"name":"matlab"},{"name":"Octave"},{"name":"機械学習"},{"name":"coursera"}],"url":"http://qiita.com/katsu1110/items/423fc9ac567710a1bd9b"},{"user":{"id":"0xfffffff7","twitter_screen_name":"0xfffffff7","profile_image_url":"https://qiita-image-store.s3.amazonaws.com/0/33116/profile-images/1473686053"},"score":"9.4","id":"efbb65521d7708f2db7d","created_at":"2017-01-25T16:50:08+09:00","title":"商用利用できるオープンソースライセンスはけっきょくどれで何をすればいいのか？","rank":20,"tags":[{"name":"JavaScript"},{"name":"npm"},{"name":"ライセンス"},{"name":"オープンソース"}],"url":"http://qiita.com/0xfffffff7/items/efbb65521d7708f2db7d"},{"user":{"id":"t_nakayama0714","twitter_screen_name":"t_nakayama0714","profile_image_url":"https://qiita-image-store.s3.amazonaws.com/0/45253/profile-images/1473690211"},"score":"9.1","id":"c312bc5edcce6c214856","created_at":"2017-01-26T04:25:05+09:00","title":"バージョンにあれこれ考えを巡らせてみる","rank":21,"tags":[{"name":"ポエム"},{"name":"バージョン管理"},{"name":"コミュニケーション"},{"name":"バージョン"}],"url":"http://qiita.com/t_nakayama0714/items/c312bc5edcce6c214856"},{"user":{"id":"sonatard","twitter_screen_name":"sonatard","profile_image_url":"https://qiita-image-store.s3.amazonaws.com/0/54186/profile-images/1473693289"},"score":"8.8","id":"815ba89e472047e38ca5","created_at":"2017-01-31T09:24:16+09:00","title":"Go Binary Hacks - GoのシステムコールとGo本体のビルド  #golang","rank":22,"tags":[{"name":"Go"},{"name":"assembly"},{"name":"C言語"}],"url":"http://qiita.com/sonatard/items/815ba89e472047e38ca5"},{"user":{"id":"YoshikawaMasashi","twitter_screen_name":"jokermarshi","profile_image_url":"https://qiita-image-store.s3.amazonaws.com/0/128182/profile-images/1473717121"},"score":"8.1","id":"51b82a7b990d51bd98cd","created_at":"2017-01-26T02:00:05+09:00","title":"\u001dPythonでベイズ最適化を行うパッケージ GPyOpt","rank":23,"tags":[{"name":"Python"},{"name":"機械学習"},{"name":"最適化"},{"name":"ベイズ最適化"}],"url":"http://qiita.com/YoshikawaMasashi/items/51b82a7b990d51bd98cd"},{"user":{"id":"cognitom","twitter_screen_name":"cognitom","profile_image_url":"https://qiita-image-store.s3.amazonaws.com/0/1858/profile-images/1473683914"},"score":"8.1","id":"af29c3d23931f19c37d8","created_at":"2017-01-29T21:46:28+09:00","title":"Highlandで流れるようにスクレーピングする話","rank":24,"tags":[{"name":"Node"},{"name":"Stream"},{"name":"highland"},{"name":"openBD"}],"url":"http://qiita.com/cognitom/items/af29c3d23931f19c37d8"},{"user":{"id":"pashango2","twitter_screen_name":"pashango2","profile_image_url":"https://qiita-image-store.s3.amazonaws.com/0/140075/profile-images/1481911279"},"score":"7.1","id":"145d858eff3c505c100a","created_at":"2017-01-31T08:36:06+09:00","title":"PIL/Pillow チートシート","rank":25,"tags":[{"name":"Python"},{"name":"PIL"},{"name":"pillow"}],"url":"http://qiita.com/pashango2/items/145d858eff3c505c100a"},{"user":{"id":"ovrmrw","twitter_screen_name":"ovrmrw","profile_image_url":"https://qiita-image-store.s3.amazonaws.com/0/74793/profile-images/1475128036"},"score":"6.7","id":"b45d7bf29c8d29415bd7","created_at":"2017-01-30T23:19:46+09:00","title":"RxJSのconcatMap, mergeMap, switchMapの違いを理解する(中級者向け)","rank":26,"tags":[{"name":"RxJS"}],"url":"http://qiita.com/ovrmrw/items/b45d7bf29c8d29415bd7"},{"user":{"id":"hoge_star","twitter_screen_name":"sr_rintaro","profile_image_url":"https://qiita-image-store.s3.amazonaws.com/0/133151/profile-images/1473718872"},"score":"6.7","id":"f802cdb0842462e4a6ce","created_at":"2017-01-25T23:41:05+09:00","title":"新卒エンジニアが上司からの機能変更に揉まれまくって気が付いた事","rank":27,"tags":[{"name":"PHP"},{"name":"JavaScript"},{"name":"iOS"},{"name":"初心者"}],"url":"http://qiita.com/hoge_star/items/f802cdb0842462e4a6ce"},{"user":{"id":"tanakahisateru","twitter_screen_name":"tanakahisateru","profile_image_url":"https://qiita-image-store.s3.amazonaws.com/0/11525/profile-images/1473682056"},"score":"6.5","id":"d8a67ad89c07baf8c0da","created_at":"2017-01-27T03:30:25+09:00","title":"IntelliJとかJVMのIDE使いでもKarabinerなしでバックスラッシュを片手入力したい","rank":28,"tags":[{"name":"Mac"},{"name":"IntelliJ"},{"name":"JVM"},{"name":"バックスラッシュ"},{"name":"Hammerspoon"}],"url":"http://qiita.com/tanakahisateru/items/d8a67ad89c07baf8c0da"},{"user":{"id":"tonkotsuboy_com","twitter_screen_name":"tonkotsuboy_com","profile_image_url":"https://qiita-image-store.s3.amazonaws.com/0/67884/profile-images/1473697671"},"score":"6.3","id":"32b56eef5c8114cae43c","created_at":"2017-01-27T11:44:02+09:00","title":"GulpやSassを使う時に覚えて幸せになったnpmの便利な使い方","rank":29,"tags":[{"name":"JavaScript"},{"name":"Node.js"},{"name":"npm"},{"name":"gulp"}],"url":"http://qiita.com/tonkotsuboy_com/items/32b56eef5c8114cae43c"},{"user":{"id":"kopanitsa","profile_image_url":"https://qiita-image-store.s3.amazonaws.com/0/42108/profile-images/1473689040"},"score":"6.3","id":"7d37b5b2f7fc3b79ce76","created_at":"2017-01-29T17:57:37+09:00","title":"Respeakerで音声認識を行う","rank":30,"tags":[{"name":"IoT"},{"name":"ReSpeaker"}],"url":"http://qiita.com/kopanitsa/items/7d37b5b2f7fc3b79ce76"}]