[{"user":{"id":"icoxfog417","twitter_screen_name":"icoxfog417","profile_image_url":"https://qiita-image-store.s3.amazonaws.com/0/25990/profile-images/1484303516"},"score":"132.9","id":"d06651db10e27220c819","created_at":"2017-10-18T15:22:25+09:00","title":"大自然言語時代のための、文章要約","rank":1,"tags":[{"name":"Python"},{"name":"自然言語処理"},{"name":"機械学習"},{"name":"MachineLearning"}],"url":"http://qiita.com/icoxfog417/items/d06651db10e27220c819"},{"user":{"id":"satoru_mag","twitter_screen_name":"satoluxx","profile_image_url":"https://qiita-image-store.s3.amazonaws.com/0/49108/profile-images/1475855544"},"score":"54.6","id":"f2e42b8264c86fca80f2","created_at":"2017-10-15T15:56:54+09:00","title":"Dataprepで国勢調査のデータをBigQueryに入れてみる。","rank":2,"tags":[{"name":"オープンデータ"},{"name":"gcpja"},{"name":"bigquery"},{"name":"gcp"},{"name":"Dataprep"}],"url":"http://qiita.com/satoru_mag/items/f2e42b8264c86fca80f2"},{"user":{"id":"aqubi","twitter_screen_name":"aqubi","profile_image_url":"https://qiita-image-store.s3.amazonaws.com/0/1380/profile-images/1473683412"},"score":"48.4","id":"8b3c4dcd208e2581184d","created_at":"2017-10-16T04:22:48+09:00","title":"iOS11のInsetsとLayout","rank":3,"tags":[{"name":"iOS"},{"name":"UIKit"},{"name":"ios11"}],"url":"http://qiita.com/aqubi/items/8b3c4dcd208e2581184d"},{"user":{"id":"mebiusbox2","twitter_screen_name":"mebiusbox2","profile_image_url":"https://qiita-image-store.s3.amazonaws.com/0/133092/profile-images/1473718852"},"score":"41.2","id":"1b69ccf5d76b173350e5","created_at":"2017-10-14T21:57:23+09:00","title":"CGのための確率・統計入門","rank":4,"tags":[{"name":"数学"},{"name":"統計"},{"name":"CG"},{"name":"確率"}],"url":"http://qiita.com/mebiusbox2/items/1b69ccf5d76b173350e5"},{"user":{"id":"alchemist","profile_image_url":"https://gravatar.com/avatar/75b4f964a862618833d636ecb33f2272?d=https%3A%2F%2Fidenticons.github.com%2F7075b35798fc3d5f5b6e7f2954151215.png&r=x"},"score":"28.1","id":"83c50712d9cf0e51e750","created_at":"2017-10-14T11:03:26+09:00","title":"GPUでディープラーニングやるならAWSよりFloydHub","rank":5,"tags":[{"name":"DeepLearning"},{"name":"Keras"},{"name":"TensorFlow"},{"name":"Floydhub"}],"url":"http://qiita.com/alchemist/items/83c50712d9cf0e51e750"},{"user":{"id":"little_hand_s","twitter_screen_name":"little_hand_s","profile_image_url":"https://qiita-image-store.s3.amazonaws.com/0/30489/profile-images/1473685506"},"score":"18.1","id":"a0b6ff6fa092f95b89b3","created_at":"2017-10-16T00:14:57+09:00","title":"モデルとは\"現実世界を正しく表現したもの\"ではないという話 / 境界付けられたコンテキストの必要性","rank":6,"tags":[{"name":"Java"},{"name":"オブジェクト指向"},{"name":"DDD"},{"name":"設計"},{"name":"ドメイン駆動設計"}],"url":"http://qiita.com/little_hand_s/items/a0b6ff6fa092f95b89b3"},{"user":{"id":"jnchito","twitter_screen_name":"jnchito","profile_image_url":"https://qiita-image-store.s3.amazonaws.com/0/7465/profile-images/1500323590"},"score":"11.7","id":"3a8d19fd9a30468cafd4","created_at":"2017-10-16T04:54:25+09:00","title":"【翻訳】RSpecのリードメンテナだけど何か質問ある？","rank":7,"tags":[{"name":"Ruby"},{"name":"RSpec"}],"url":"http://qiita.com/jnchito/items/3a8d19fd9a30468cafd4"},{"user":{"id":"mizchi","twitter_screen_name":"mizchi","profile_image_url":"https://qiita-image-store.s3.amazonaws.com/0/1727/profile-images/1473683814"},"score":"10.8","id":"60722563b8a938e7336f","created_at":"2017-10-19T05:08:44+09:00","title":"Next.js を Firebase hosting で動かしてSSRする","rank":8,"tags":[{"name":"gcp"},{"name":"Firebase"},{"name":"next.js"}],"url":"http://qiita.com/mizchi/items/60722563b8a938e7336f"},{"user":{"id":"gcmae","twitter_screen_name":"voyagesister","profile_image_url":"https://qiita-image-store.s3.amazonaws.com/0/159013/profile-images/1496188551"},"score":"8.0","id":"9b4ab7ea35e378da2c70","created_at":"2017-10-19T00:37:41+09:00","title":"JavaScriptで、Cognitoコード認証フローを実装したまとめ","rank":9,"tags":[{"name":"JavaScript"},{"name":"AWS"},{"name":"aws-sdk"},{"name":"cognito"}],"url":"http://qiita.com/gcmae/items/9b4ab7ea35e378da2c70"},{"user":{"id":"nju33","twitter_screen_name":"nju33_ki","profile_image_url":"https://qiita-image-store.s3.amazonaws.com/0/84144/profile-images/1496803139"},"score":"7.5","id":"b54fe4fcaced2e0328dc","created_at":"2017-10-15T15:16:34+09:00","title":"Qiitaをズァーって感じで広く見るアプリ","rank":10,"tags":[{"name":"Qiita"},{"name":"アプリ"},{"name":"Electron"}],"url":"http://qiita.com/nju33/items/b54fe4fcaced2e0328dc"},{"user":{"id":"potato4d","twitter_screen_name":"potato4d","profile_image_url":"https://qiita-image-store.s3.amazonaws.com/0/75633/profile-images/1506191759"},"score":"6.6","id":"1b92df0cbf9b0b6cf8d6","created_at":"2017-10-19T15:57:04+09:00","title":"Vue.jsのpropsカスタムバリデーターを使った堅牢なコンポーネント作成","rank":11,"tags":[{"name":"JavaScript"},{"name":"vue.js"}],"url":"http://qiita.com/potato4d/items/1b92df0cbf9b0b6cf8d6"},{"user":{"id":"udon11","profile_image_url":"https://qiita-image-store.s3.amazonaws.com/0/67158/profile-images/1473697435"},"score":"6.3","id":"fef44cec7b243f93151b","created_at":"2017-10-14T16:45:19+09:00","title":"Google Homeで時報を知らせる","rank":12,"tags":[{"name":"Node.js"},{"name":"RaspberryPi"},{"name":"IoT"},{"name":"GoogleHome"}],"url":"http://qiita.com/udon11/items/fef44cec7b243f93151b"},{"user":{"id":"saturday06","twitter_screen_name":"saturday06","profile_image_url":"https://qiita-image-store.s3.amazonaws.com/0/26528/profile-images/1473684614"},"score":"4.7","id":"333fcdf5b3b8030c9b05","created_at":"2017-10-18T08:11:11+09:00","title":"WebUSBでFeliCaの一意なIDであるIDmを読む","rank":13,"tags":[{"name":"JavaScript"},{"name":"NFC"},{"name":"FeliCa"},{"name":"WebUSB"}],"url":"http://qiita.com/saturday06/items/333fcdf5b3b8030c9b05"},{"user":{"id":"qwerty8t","profile_image_url":"https://secure.gravatar.com/avatar/337ae9c8c92ad3a34fad812b142c19e1"},"score":"4.3","id":"2aa1c91e15aeb504df9c","created_at":"2017-10-16T23:24:33+09:00","title":"ハンバーガーメニューデザインの提案","rank":14,"tags":[{"name":"HTML"},{"name":"CSS"},{"name":"jQuery"},{"name":"Design"}],"url":"http://qiita.com/qwerty8t/items/2aa1c91e15aeb504df9c"},{"user":{"id":"volpe28v","profile_image_url":"https://qiita-image-store.s3.amazonaws.com/0/4195/profile-images/1508426907"},"score":"4.0","id":"16c4556c5295f5acaacc","created_at":"2017-10-18T00:36:40+09:00","title":"ツリーマップでタスクの規模を可視化するタスク管理ツールを作ってみた","rank":15,"tags":[{"name":"Node.js"},{"name":"MongoDB"},{"name":"Socket.io"},{"name":"d3.js"},{"name":"タスク管理"}],"url":"http://qiita.com/volpe28v@github/items/16c4556c5295f5acaacc"},{"user":{"id":"kabosusoba","twitter_screen_name":"kabosusoba","profile_image_url":"https://qiita-image-store.s3.amazonaws.com/0/198108/profile-images/1506527560"},"score":"2.7","id":"200d14c68b8c0e5b2092","created_at":"2017-10-16T20:26:52+09:00","title":"何故DIコンテナが必要なのか","rank":16,"tags":[{"name":"TypeScript"},{"name":"DI"},{"name":"DependencyInjection"}],"url":"http://qiita.com/kabosusoba/items/200d14c68b8c0e5b2092"},{"user":{"id":"takemotto","profile_image_url":"https://qiita-image-store.s3.amazonaws.com/0/95324/profile-images/1473706534"},"score":"2.6","id":"1f75812e822fccfb7612","created_at":"2017-10-16T18:20:48+09:00","title":"差分バックアップツール「borg」を試してみた","rank":17,"tags":[{"name":"backup"},{"name":"borg"}],"url":"http://qiita.com/takemotto/items/1f75812e822fccfb7612"},{"user":{"id":"enomotok_","twitter_screen_name":"enomotok_","profile_image_url":"https://qiita-image-store.s3.amazonaws.com/0/39720/profile-images/1503898551"},"score":"2.1","id":"696b10866e33303ab3d4","created_at":"2017-10-20T11:17:22+09:00","title":"過去のiOS beta版の配信スケジュール","rank":18,"tags":[{"name":"iPhone"},{"name":"iPad"},{"name":"iOS"}],"url":"http://qiita.com/enomotok_/items/696b10866e33303ab3d4"},{"user":{"id":"masakielastic","profile_image_url":"https://qiita-image-store.s3.amazonaws.com/0/349/profile-images/1473683889"},"score":"2.1","id":"dd98af4be0968441bc03","created_at":"2017-10-17T09:42:48+09:00","title":"Unicode から求めることができないレガシーエンコーディングのコードポイントを調べる","rank":19,"tags":[{"name":"Ruby"},{"name":"文字コード"},{"name":"unicode"}],"url":"http://qiita.com/masakielastic/items/dd98af4be0968441bc03"},{"user":{"id":"QUANON","twitter_screen_name":"quanon_jp","profile_image_url":"https://qiita-image-store.s3.amazonaws.com/0/6697/profile-images/1508248323"},"score":"1.9","id":"77ce3a9e7e33dbed489b","created_at":"2017-10-16T22:29:59+09:00","title":"f-strings の使用例","rank":20,"tags":[{"name":"Python"}],"url":"http://qiita.com/QUANON/items/77ce3a9e7e33dbed489b"},{"user":{"id":"matsuda_vla","twitter_screen_name":"hmtd223","profile_image_url":"https://qiita-image-store.s3.amazonaws.com/0/207715/profile-images/1508172003"},"score":"1.8","id":"9922e34e7623900eadc1","created_at":"2017-10-17T01:42:39+09:00","title":"SudachiをElasticsearchで使用する手順#1","rank":21,"tags":[{"name":"NLP"},{"name":"Elasticsearch"},{"name":"形態素解析"},{"name":"Sudachi"}],"url":"http://qiita.com/matsuda_vla/items/9922e34e7623900eadc1"},{"user":{"id":"ababup1192","twitter_screen_name":"ababupdownba","profile_image_url":"https://qiita-image-store.s3.amazonaws.com/0/48687/profile-images/1473691441"},"score":"1.7","id":"d6ca1af6efcbac8d550f","created_at":"2017-10-16T23:25:19+09:00","title":"関数型言語Elmでテスト駆動開発(第1~4章)","rank":22,"tags":[{"name":"TDD"},{"name":"テスト"},{"name":"Elm"},{"name":"関数型プログラミング"}],"url":"http://qiita.com/ababup1192/items/d6ca1af6efcbac8d550f"},{"user":{"id":"mizchi","twitter_screen_name":"mizchi","profile_image_url":"https://qiita-image-store.s3.amazonaws.com/0/1727/profile-images/1473683814"},"score":"1.6","id":"8af2cbbf827dd0567796","created_at":"2017-10-16T17:09:24+09:00","title":"Hypernova/Webpacker/Turbolinks でSSRできてSPA風に動くスケルトンを作った","rank":23,"tags":[{"name":"Rails"},{"name":"webpack"},{"name":"hypernova"},{"name":"webpacker"}],"url":"http://qiita.com/mizchi/items/8af2cbbf827dd0567796"},{"user":{"id":"gnk263","profile_image_url":"https://avatars2.githubusercontent.com/u/26545706?v=4"},"score":"1.5","id":"d2ad1f0525ced46effa8","created_at":"2017-10-18T07:08:20+09:00","title":"Xamarin.FormsでGoogle Analyticsに対応してみた(再掲)","rank":24,"tags":[{"name":"GoogleAnalytics"},{"name":"Xamarin"},{"name":"Xamarin.Forms"}],"url":"http://qiita.com/gnk263/items/d2ad1f0525ced46effa8"},{"user":{"id":"QUANON","twitter_screen_name":"quanon_jp","profile_image_url":"https://qiita-image-store.s3.amazonaws.com/0/6697/profile-images/1508248323"},"score":"1.5","id":"1b8535a268ac4613fbeb","created_at":"2017-10-14T13:21:43+09:00","title":"ping 成功時にビープ音を鳴らす","rank":25,"tags":[{"name":"Linux"},{"name":"Sound"},{"name":"beep"}],"url":"http://qiita.com/QUANON/items/1b8535a268ac4613fbeb"},{"user":{"id":"teradonburi","twitter_screen_name":"teradonburi","profile_image_url":"https://qiita-image-store.s3.amazonaws.com/0/55077/profile-images/1478700761"},"score":"1.4","id":"fb91e5feacab5071cfef","created_at":"2017-10-15T16:50:58+09:00","title":"ReactJSで作る今時のSPA入門","rank":26,"tags":[{"name":"JavaScript"},{"name":"webpack"},{"name":"React"},{"name":"babel"},{"name":"redux"}],"url":"http://qiita.com/teradonburi/items/fb91e5feacab5071cfef"},{"user":{"id":"tomueeen93","profile_image_url":"https://qiita-image-store.s3.amazonaws.com/0/59499/profile-images/1473694949"},"score":"1.4","id":"c9529408f0e852382ecb","created_at":"2017-10-14T17:05:20+09:00","title":"Qiitaに投稿するのって大切なのではないかという話(初投稿)","rank":27,"tags":[{"name":"Qiita"},{"name":"メモ"},{"name":"初心者"}],"url":"http://qiita.com/tomueeen93/items/c9529408f0e852382ecb"},{"user":{"id":"jagainu","twitter_screen_name":"jagainu","profile_image_url":"https://qiita-image-store.s3.amazonaws.com/0/73759/profile-images/1473761998"},"score":"1.4","id":"2a1e3779f944588d29de","created_at":"2017-10-17T20:34:25+09:00","title":"パワーアップしたKernelでKaggleに飛び込もう","rank":28,"tags":[{"name":"機械学習"},{"name":"Jupyter"},{"name":"Kaggle"}],"url":"http://qiita.com/jagainu/items/2a1e3779f944588d29de"},{"user":{"id":"nori-dev-akg","profile_image_url":"https://qiita-image-store.s3.amazonaws.com/0/203949/profile-images/1506822002"},"score":"1.3","id":"f9119612c46fcddfb5e2","created_at":"2017-10-15T17:24:21+09:00","title":"朝専用ダッシュボード onTV  #powered by RaspberryPi and Dashing","rank":29,"tags":[{"name":"Ruby"},{"name":"RaspberryPi"},{"name":"Dashing"},{"name":"デジタルサイネージ"},{"name":"kiosk"}],"url":"http://qiita.com/nori-dev-akg/items/f9119612c46fcddfb5e2"},{"user":{"id":"yama-t","profile_image_url":"https://qiita-image-store.s3.amazonaws.com/0/46299/profile-images/1473690606"},"score":"1.3","id":"53d16318198d0765e5a0","created_at":"2017-10-17T20:01:12+09:00","title":"「エンジニアの転職メモ」の内容を実践した結果","rank":30,"tags":[{"name":"ポエム"},{"name":"転職"},{"name":"キャリア"}],"url":"http://qiita.com/yama-t/items/53d16318198d0765e5a0"}]